clisya/__init__.py
clisya/schedule.py
clisya-1.1.dist-info/METADATA
clisya-1.1.dist-info/WHEEL
clisya-1.1.dist-info/top_level.txt
clisya-1.1.dist-info/RECORD
